ritual_irys/__init__.py
ritual_irys/__main__.py
ritual_irys/cli.py
ritual_irys/concurrency_utils.py
ritual_irys/file_manager.py
ritual_irys/gateway.py
ritual_irys/http.py
ritual_irys/manifest.py
ritual_irys/py.typed
ritual_irys/repo_manager.py
ritual_irys/types.py
ritual_irys/utils.py
ritual_irys/version.py
ritual_irys-0.1.1.dist-info/METADATA
ritual_irys-0.1.1.dist-info/WHEEL
ritual_irys-0.1.1.dist-info/entry_points.txt
ritual_irys-0.1.1.dist-info/RECORD
