Metadata-Version: 2.1
Name: ritual_irys
Version: 0.1.1
Summary: The Library + CLI to upload/download Ritual files and repositories to Irys
Author: Jesse Wright
Author-email: jesse@irys.xyz
Requires-Python: >=3.12,<4.0
Classifier: Programming Language :: Python :: 3
Classifier: Programming Language :: Python :: 3.12
Classifier: Programming Language :: Python :: 3.13
Requires-Dist: aiohttp (==3.10.5)
Requires-Dist: click (==8.1.7)
Requires-Dist: irys-sdk (>=0.1.3,<0.2.0)
Requires-Dist: nicelog (>=0.3,<0.4)
Requires-Dist: pydantic (==2.5.3)
Requires-Dist: python-dotenv (==1.0.0)
Requires-Dist: reretry (==0.11.8)
Requires-Dist: rich (==13.7.1)
Requires-Dist: tqdm (==4.65.1)
Requires-Dist: web3 (==7.4.0)
